setup.py
isom5650/__init__.py
isom5650/data.py
isom5650/metrics.py
isom5650/regression.py
isom5650/timeseries.py
isom5650.egg-info/Icon
isom5650.egg-info/PKG-INFO
isom5650.egg-info/SOURCES.txt
isom5650.egg-info/dependency_links.txt
isom5650.egg-info/requires.txt
isom5650.egg-info/top_level.txt