Metadata-Version: 2.1
Name: isom5650
Version: 0.2.3
Summary: Do not distribute it without permission. 
Author: Xuhu Wan
Author-email: xuhu.wan@gmail.com
Requires-Dist: numpy
Requires-Dist: pandas
Requires-Dist: plotly
Requires-Dist: yfinance
Requires-Dist: statsmodels
